{
  "_cacheVersion": 5,
  "qid": "Q931871",
  "name": "Franciscus Gomarus",
  "slug": "franciscus-gomarus",
  "birthYear": 1563,
  "deathYear": 1641,
  "imageUrl": "http://commons.wikimedia.org/wiki/Special:FilePath/Gomarus.jpg",
  "wikipediaUrl": "https://en.wikipedia.org/wiki/Franciscus_Gomarus",
  "prdlId": "105",
  "familyName": null,
  "givenName": "Franciscus",
  "openLibraryId": "OL6061775A",
  "labels": {
    "nl": "Franciscus Gomarus",
    "en": "Franciscus Gomarus",
    "arz": "فرانسيسكوس جوماروس",
    "ast": "Franciscus Gomarus",
    "ca": "Franciscus Gomarus",
    "cs": "Franciscus Gomarus",
    "da": "Franciscus Gomarus",
    "de": "Franciscus Gomarus",
    "es": "Franciscus Gomarus",
    "eu": "Franciscus Gomarus",
    "fi": "Franciscus Gomarus",
    "fr": "Franciscus Gomarus",
    "fy": "Franciscus Gomarus",
    "ga": "Franciscus Gomarus",
    "it": "Franciscus Gomarus",
    "ja": "フランシスクス・ホマルス",
    "ko": "호마루스",
    "la": "Franciscus Gomarus",
    "mul": "Franciscus Gomarus",
    "nb": "Franciscus Gomarus",
    "nn": "Franciscus Gomarus",
    "pt": "Franciscus Gomarus",
    "pt-br": "Franciscus Gomarus",
    "ru": "Францискус Гомарус",
    "sq": "Franciscus Gomarus",
    "sv": "Frans Gomarus",
    "tr": "Franciscus Gomarus",
    "zh": "弗朗西斯库斯·戈马尔",
    "zh-cn": "弗朗西斯库斯·戈马尔",
    "zh-hans": "弗朗西斯库斯·戈马尔",
    "zh-hant": "弗朗西斯庫斯·戈馬爾",
    "hy": "Ֆրանցիսկուս Գոմարուս"
  }
}